rephunt/__init__.py
rephunt/__main__.py
rephunt/rephunt.py
rephunt-0.1.2.dist-info/LICENSE.md
rephunt-0.1.2.dist-info/METADATA
rephunt-0.1.2.dist-info/WHEEL
rephunt-0.1.2.dist-info/top_level.txt
rephunt-0.1.2.dist-info/RECORD
